docs/assets/logo3-cut.webp
interlab/.idea/.gitignore
interlab/.idea/inspectionProfiles/Project_Default.xml
interlab/.idea/inspectionProfiles/profiles_settings.xml
interlab/.idea/interlab.iml
interlab/.idea/misc.xml
interlab/.idea/modules.xml
interlab/.idea/vcs.xml
interlab/__init__.py
interlab/__version__.py
interlab/actor/__init__.py
interlab/actor/base.py
interlab/actor/llm_actor.py
interlab/actor/memory/__init__.py
interlab/actor/memory/base.py
interlab/actor/memory/experimental/__init__.py
interlab/actor/memory/experimental/embedding_memory.py
interlab/actor/memory/experimental/summarizing_memory.py
interlab/actor/memory/list_memory.py
interlab/actor/web_console_actor.py
interlab/environment/__init__.py
interlab/environment/base.py
interlab/environment/experimental/__init__.py
interlab/environment/experimental/commgame.py
interlab/environment/experimental/monitor.py
interlab/environment/experimental/negotiation.py
interlab/environment/experimental/tree.py
interlab/queries/__init__.py
interlab/queries/count_tokens.py
interlab/queries/experimental/repeat.py
interlab/queries/experimental/simple_tag_parsing.py
interlab/queries/json_examples.py
interlab/queries/json_parsing.py
interlab/queries/json_schema.py
interlab/queries/query_failure.py
interlab/queries/query_for_json.py
interlab/queries/query_model.py
interlab/queries/summarize.py
interlab/queries/web_console.py
interlab/utils/__init__.py
interlab/utils/copying.py
interlab/utils/text.py
interlab_zoo/__init__.py
interlab_zoo/actors/simple_cot_actor.py
requirements-colab.txt
requirements-full.txt
requirements.txt
treetrace/__init__.py
treetrace/ext/google_colab.py
treetrace/ext/graphviz.py
treetrace/ext/pyplot.py
treetrace/tracing/data/__init__.py
treetrace/tracing/data/blob.py
treetrace/tracing/data/format_str.py
treetrace/tracing/data/html.py
treetrace/tracing/serialization.py
treetrace/tracing/storage.py
treetrace/tracing/tracingnode.py
treetrace/ui/__init__.py
treetrace/ui/__main__.py
interlab-0.4.1.dist-info/LICENSE
interlab-0.4.1.dist-info/METADATA
interlab-0.4.1.dist-info/WHEEL
interlab-0.4.1.dist-info/RECORD
