Metadata-Version: 2.1
Name: interlab
Version: 0.4.1
Summary: A research framework for artificial agent interactions
Author: Tomas Gavenciak
Author-email: gavento@acsresearch.org
Requires-Python: >=3.10,<4.0
Classifier: Programming Language :: Python :: 3
Classifier: Programming Language :: Python :: 3.10
Classifier: Programming Language :: Python :: 3.11
Requires-Dist: addict (>=2.4.0,<3.0.0)
Requires-Dist: anthropic (>=0.10.0,<0.11.0)
Requires-Dist: cachetools (>=5.3.2,<6.0.0)
Requires-Dist: dirtyjson (>=1.0.8,<2.0.0)
Requires-Dist: fastapi (>=0.109.0,<0.110.0)
Requires-Dist: jsonref (>=1.1.0,<2.0.0)
Requires-Dist: langchain (>=0.1.1,<0.2.0)
Requires-Dist: langchain-openai (>=0.0.3,<0.0.4)
Requires-Dist: matplotlib (>=3.7.1,<4.0.0)
Requires-Dist: openai (>=1.8.0,<2.0.0)
Requires-Dist: pydantic (>=1.9.0,<2.0.0)
Requires-Dist: python-dotenv (>=1.0.0,<2.0.0)
Requires-Dist: tiktoken (>=0.5.2,<0.6.0)
Requires-Dist: tqdm (>=4.65.0,<5.0.0)
Requires-Dist: uvicorn[standard] (>=0.26.0,<0.27.0)
